{
 "actions": [],
 "creation": "2022-04-28 15:46:59.736928",
 "doctype": "DocType",
 "editable_grid": 1,
 "engine": "InnoDB",
 "field_order": [
  "bank_account",
  "is_default"
 ],
 "fields": [
  {
   "fieldname": "bank_account",
   "fieldtype": "Link",
   "in_list_view": 1,
   "label": "Bank Account",
   "options": "Bank Account"
  },
  {
   "default": "0",
   "fetch_from": "bank_account.is_default",
   "fieldname": "is_default",
   "fieldtype": "Check",
   "in_list_view": 1,
   "label": "Is Default",
   "read_only": 1
  }
 ],
 "index_web_pages_for_search": 1,
 "istable": 1,
 "links": [],
 "modified": "2022-05-17 16:55:50.983751",
 "modified_by": "Administrator",
 "module": "NGO",
 "name": "Donor Bank detail",
 "owner": "Administrator",
 "permissions": [],
 "sort_field": "modified",
 "sort_order": "DESC",
 "track_changes": 1
}